[{"message":"**STAFF MEMBER Lucas** gave ammo-rifle2 (x1000) to Lucas","from":"adminactions","time":1712950765,"title":"Set Gang"},{"message":"**STAFF MEMBER Lucas** revived **Lucas** [2]","from":"adminactions","time":1713133064,"title":"Revive"},{"message":"**STAFF MEMBER Lucas** revived **Lucas** [2]","from":"adminactions","time":1713133477,"title":"Revive"},{"message":"**STAFF MEMBER Lucas** revived **Lucas** [2]","from":"adminactions","time":1713133484,"title":"Revive"},{"message":"**STAFF MEMBER Lucas** fed and watered **Lucas** [2]","from":"adminactions","time":1713133485,"title":"Food & Water Max"},{"message":"**STAFF MEMBER Lucas** relieved stress of **Lucas** [2]","from":"adminactions","time":1713133487,"title":"Relieve Stress"},{"message":"**STAFF MEMBER Lucas** opened skin menu for Lucas","from":"adminactions","time":1713133492,"title":"Skin Menu"}]